firebird/base/__about__.py
firebird/base/__init__.py
firebird/base/buffer.py
firebird/base/collections.py
firebird/base/config.py
firebird/base/config_pb2.py
firebird/base/config_pb2.pyi
firebird/base/hooks.py
firebird/base/logging.py
firebird/base/protobuf.py
firebird/base/signal.py
firebird/base/strconv.py
firebird/base/trace.py
firebird/base/types.py
firebird_base-2.0.1.dist-info/METADATA
firebird_base-2.0.1.dist-info/WHEEL
firebird_base-2.0.1.dist-info/entry_points.txt
firebird_base-2.0.1.dist-info/licenses/LICENSE
firebird_base-2.0.1.dist-info/RECORD
