Metadata-Version: 2.4
Name: firebird-base
Version: 2.0.1
Summary: Firebird base modules for Python
Project-URL: Home, https://github.com/FirebirdSQL/python3-base
Project-URL: Documentation, https://firebird-base.rtfd.io
Project-URL: Issues, https://github.com/FirebirdSQL/python3-base/issues
Project-URL: Funding, https://github.com/sponsors/pcisar
Project-URL: Source, https://github.com/FirebirdSQL/python3-base
Author-email: Pavel Cisar <pcisar@users.sourceforge.net>
License: 
License-File: LICENSE
Keywords: Collections,Configuration,Firebird,Hooks,Logging,Protobuf,Signals,Trace
Classifier: Development Status :: 5 - Production/Stable
Classifier: Intended Audience :: Developers
Classifier: License :: OSI Approved :: MIT License
Classifier: Operating System :: MacOS
Classifier: Operating System :: Microsoft :: Windows
Classifier: Operating System :: POSIX :: Linux
Classifier: Programming Language :: Python :: 3 :: Only
Classifier: Programming Language :: Python :: 3.11
Classifier: Programming Language :: Python :: 3.12
Classifier: Programming Language :: Python :: 3.13
Classifier: Topic :: Software Development
Requires-Python: <4,>=3.11
Requires-Dist: protobuf~=5.29
